{
  "published": true,
  "pages": [
    {
      "elements": [
        {
          "type": "text",
          "name": "birth_year",
          "title": "What is your year of birth? ",
          "description": "Please enter a whole number e.g. 1975. ",
          "inputType": "number",
          "min": 1930,
          "max": 2000,
          "placeHolder": "enter a number"
        },
        {
          "type": "radiogroup",
          "name": "cdo_teaching_experience",
          "title": "Which of the following options best captures your previous experience using Code.org in the classroom?",
          "choices": [
            {
              "value": "cs_teaching",
              "text": " I use Code.org to teach a computer science course"
            },
            {
              "value": "co_curricular_teaching",
              "text": " I use Code.org to introduce computer science when teaching other content"
            },
            {
              "value": "hoc",
              "text": "My students have done Hour of Code activities"
            },
            {
              "value": "not_used",
              "text": "I have not used Code.org in my classroom yet"
            }
          ]
        },
        {
          "type": "radiogroup",
          "name": "gender_identity",
          "title": "What is your gender identity?",
          "choices": [
            {
              "value": "female",
              "text": "Female"
            },
            {
              "value": "male",
              "text": "Male"
            },
            {
              "value": "non_binary",
              "text": "Non-binary"
            },
            {
              "value": "not_listed",
              "text": "Preferred term not listed"
            },
            {
              "value": "no_answer",
              "text": "Prefer not to answer"
            }
          ]
        },
        {
          "type": "checkbox",
          "name": "grade",
          "title": "What grade levels do you currently support or work with?",
          "description": " (Select all that apply)",
          "choices": [
            {
              "value": "k",
              "text": "Kindergarten"
            },
            {
              "value": "1",
              "text": "1st grade"
            },
            {
              "value": "2",
              "text": "2nd grade"
            },
            {
              "value": "3",
              "text": "3rd grade"
            },
            {
              "value": "4",
              "text": "4th grade"
            },
            {
              "value": "5",
              "text": "5th grade"
            },
            {
              "value": "6",
              "text": "6th grade"
            },
            {
              "value": "7",
              "text": "7th grade"
            },
            {
              "value": "8",
              "text": "8th grade"
            },
            {
              "value": "9",
              "text": "9th grade"
            },
            {
              "value": "10",
              "text": "10th grade"
            },
            {
              "value": "11",
              "text": "11th grade"
            },
            {
              "value": "12",
              "text": "12th grade"
            },
            {
              "value": "12up",
              "text": "Above 12th grade"
            },
            {
              "value": "na",
              "text": "N/A"
            }
          ]
        },
        {
          "type": "radiogroup",
          "name": "highest_level_cs_education",
          "title": "Which most accurately describes the highest level of formal computer science education you have completed? ",
          "otherPlaceHolder": "Other CS Education",
          "choices": [
            {
              "value": "little_no",
              "text": "At this time, I have little to no formal education in computer science."
            },
            {
              "value": "online_courses",
              "text": "I have taken one or more courses online for credit."
            },
            {
              "value": "college_courses",
              "text": "I took one or more courses in college."
            },
            {
              "value": "earning_degree",
              "text": "I am currently in the process of earning a computer science degree."
            },
            {
              "value": "bachelors_degree",
              "text": "I have a Bachelor's degree in computer science."
            },
            {
              "value": "masters_degree",
              "text": "I have a Master's degree in computer science."
            },
            {
              "value": "phd",
              "text": "I have a PhD in computer science."
            }
          ],
          "hasOther": true,
          "otherText": "Other CS Education (describe)"
        },
        {
          "type": "checkbox",
          "name": "racial_ethnic_identity",
          "title": "What is your racial or ethnic identity? [check all that apply] ",
          "choices": [
            {
              "value": "am_indian_alaska",
              "text": "American Indian/Alaska Native"
            },
            {
              "value": "asian",
              "text": "Asian"
            },
            {
              "value": "black_aa",
              "text": "Black or African American"
            },
            {
              "value": "hispanic_latino",
              "text": "Hispanic or Latino"
            },
            {
              "value": "native_hawaiin_pi",
              "text": "Native Hawaiian or other Pacific Islander"
            },
            {
              "value": "white",
              "text": "White"
            },
            {
              "value": "other_race",
              "text": "Other"
            },
            {
              "value": "no_answer",
              "text": "Prefer not to answer"
            }
          ]
        },
        {
          "type": "text",
          "name": "years_teaching",
          "title": "How many years have you taught at the K-12 level (any subject)?",
          "description": "Please enter a whole number. If you are about to start your first year teaching, enter 0.",
          "inputType": "number",
          "min": 0
        },
        {
          "type": "text",
          "name": "years_teaching_cs",
          "title": "How many years have you taught COMPUTER SCIENCE at the K-12 level?",
          "description": "Please enter a whole number. Enter 0 if it's your first year teaching computer science.",
          "inputType": "number",
          "min": 0
        }
      ]
    }
  ]
}